package com.facebook.rti.a.c;

final class e
  implements Runnable
{
  e(b paramb, String paramString) {}
  
  /* Error */
  public final void run()
  {
    // Byte code:
    //   0: aload_0
    //   1: getfield 14	com/facebook/rti/a/c/e:b	Lcom/facebook/rti/a/c/b;
    //   4: getfield 29	com/facebook/rti/a/c/b:f	Lcom/fasterxml/jackson/databind/z;
    //   7: invokevirtual 34	com/fasterxml/jackson/databind/z:f	()Lcom/fasterxml/jackson/databind/c/a;
    //   10: astore_1
    //   11: aload_1
    //   12: aload_0
    //   13: getfield 16	com/facebook/rti/a/c/e:a	Ljava/lang/String;
    //   16: invokevirtual 40	com/fasterxml/jackson/databind/c/a:h	(Ljava/lang/String;)Lcom/fasterxml/jackson/databind/c/a;
    //   19: pop
    //   20: aload_0
    //   21: getfield 14	com/facebook/rti/a/c/e:b	Lcom/facebook/rti/a/c/b;
    //   24: aconst_null
    //   25: aload_1
    //   26: aconst_null
    //   27: invokestatic 43	com/facebook/rti/a/c/b:a	(Lcom/facebook/rti/a/c/b;Lcom/fasterxml/jackson/databind/c/a;Lcom/fasterxml/jackson/databind/c/a;Lcom/fasterxml/jackson/databind/p;)Lcom/fasterxml/jackson/databind/c/u;
    //   30: astore_2
    //   31: aload_0
    //   32: getfield 14	com/facebook/rti/a/c/e:b	Lcom/facebook/rti/a/c/b;
    //   35: getfield 47	com/facebook/rti/a/c/b:d	Lcom/facebook/push/mqtt/service/bg;
    //   38: invokevirtual 52	com/facebook/push/mqtt/service/bg:a	()Lcom/facebook/push/mqtt/service/au;
    //   41: astore_1
    //   42: aload_1
    //   43: ldc 54
    //   45: aload_2
    //   46: ldc2_w 55
    //   49: invokeinterface 61 5 0
    //   54: pop
    //   55: aload_1
    //   56: invokeinterface 63 1 0
    //   61: aload_0
    //   62: getfield 14	com/facebook/rti/a/c/e:b	Lcom/facebook/rti/a/c/b;
    //   65: astore_1
    //   66: aload_1
    //   67: monitorenter
    //   68: aload_0
    //   69: getfield 14	com/facebook/rti/a/c/e:b	Lcom/facebook/rti/a/c/b;
    //   72: getfield 67	com/facebook/rti/a/c/b:i	Ljava/util/Map;
    //   75: aload_0
    //   76: getfield 16	com/facebook/rti/a/c/e:a	Ljava/lang/String;
    //   79: invokeinterface 73 2 0
    //   84: ifeq +20 -> 104
    //   87: aload_0
    //   88: getfield 14	com/facebook/rti/a/c/e:b	Lcom/facebook/rti/a/c/b;
    //   91: getfield 67	com/facebook/rti/a/c/b:i	Ljava/util/Map;
    //   94: aload_0
    //   95: getfield 16	com/facebook/rti/a/c/e:a	Ljava/lang/String;
    //   98: invokeinterface 77 2 0
    //   103: pop
    //   104: aload_0
    //   105: getfield 14	com/facebook/rti/a/c/e:b	Lcom/facebook/rti/a/c/b;
    //   108: getfield 80	com/facebook/rti/a/c/b:j	Ljava/util/Map;
    //   111: aload_0
    //   112: getfield 16	com/facebook/rti/a/c/e:a	Ljava/lang/String;
    //   115: invokeinterface 73 2 0
    //   120: ifeq +20 -> 140
    //   123: aload_0
    //   124: getfield 14	com/facebook/rti/a/c/e:b	Lcom/facebook/rti/a/c/b;
    //   127: getfield 80	com/facebook/rti/a/c/b:j	Ljava/util/Map;
    //   130: aload_0
    //   131: getfield 16	com/facebook/rti/a/c/e:a	Ljava/lang/String;
    //   134: invokeinterface 77 2 0
    //   139: pop
    //   140: aload_1
    //   141: monitorexit
    //   142: return
    //   143: astore_2
    //   144: getstatic 83	com/facebook/rti/a/c/b:a	Ljava/lang/Class;
    //   147: ldc 85
    //   149: aload_2
    //   150: invokestatic 90	com/facebook/debug/a/a:b	(Ljava/lang/Class;Ljava/lang/String;Ljava/lang/Throwable;)V
    //   153: aload_1
    //   154: invokeinterface 63 1 0
    //   159: goto -98 -> 61
    //   162: astore_2
    //   163: aload_1
    //   164: invokeinterface 63 1 0
    //   169: aload_2
    //   170: athrow
    //   171: astore_2
    //   172: aload_1
    //   173: monitorexit
    //   174: aload_2
    //   175: athrow
    // Local variable table:
    //   start	length	slot	name	signature
    //   0	176	0	this	e
    //   30	16	2	localu	com.fasterxml.jackson.databind.c.u
    //   143	7	2	localRemoteException	android.os.RemoteException
    //   162	8	2	localObject2	Object
    //   171	4	2	localObject3	Object
    // Exception table:
    //   from	to	target	type
    //   42	55	143	android/os/RemoteException
    //   42	55	162	finally
    //   144	153	162	finally
    //   68	104	171	finally
    //   104	140	171	finally
    //   140	142	171	finally
    //   172	174	171	finally
  }
}

/* Location:
 * Qualified Name:     com.facebook.rti.a.c.e
 * Java Class Version: 6 (50.0)
 * JD-Core Version:    0.7.1
 */