package com.facebook.soloader;

import java.io.File;

final class t
  implements Runnable
{
  t(s params, File paramFile1, byte[] paramArrayOfByte, v paramv, File paramFile2, l paraml) {}
  
  /* Error */
  public final void run()
  {
    // Byte code:
    //   0: aconst_null
    //   1: astore_2
    //   2: aconst_null
    //   3: astore_3
    //   4: ldc 42
    //   6: ldc 44
    //   8: invokestatic 50	android/util/Log:v	(Ljava/lang/String;Ljava/lang/String;)I
    //   11: pop
    //   12: new 52	java/io/RandomAccessFile
    //   15: dup
    //   16: aload_0
    //   17: getfield 23	com/facebook/soloader/t:a	Ljava/io/File;
    //   20: ldc 54
    //   22: invokespecial 57	java/io/RandomAccessFile:<init>	(Ljava/io/File;Ljava/lang/String;)V
    //   25: astore 4
    //   27: aload 4
    //   29: aload_0
    //   30: getfield 25	com/facebook/soloader/t:b	[B
    //   33: invokevirtual 61	java/io/RandomAccessFile:write	([B)V
    //   36: aload 4
    //   38: aload 4
    //   40: invokevirtual 65	java/io/RandomAccessFile:getFilePointer	()J
    //   43: invokevirtual 69	java/io/RandomAccessFile:setLength	(J)V
    //   46: aload 4
    //   48: invokevirtual 72	java/io/RandomAccessFile:close	()V
    //   51: new 52	java/io/RandomAccessFile
    //   54: dup
    //   55: new 74	java/io/File
    //   58: dup
    //   59: aload_0
    //   60: getfield 21	com/facebook/soloader/t:f	Lcom/facebook/soloader/s;
    //   63: getfield 77	com/facebook/soloader/c:a	Ljava/io/File;
    //   66: ldc 79
    //   68: invokespecial 80	java/io/File:<init>	(Ljava/io/File;Ljava/lang/String;)V
    //   71: ldc 54
    //   73: invokespecial 57	java/io/RandomAccessFile:<init>	(Ljava/io/File;Ljava/lang/String;)V
    //   76: astore_3
    //   77: aload_0
    //   78: getfield 27	com/facebook/soloader/t:c	Lcom/facebook/soloader/v;
    //   81: aload_3
    //   82: invokevirtual 85	com/facebook/soloader/v:a	(Ljava/io/DataOutput;)V
    //   85: aload_3
    //   86: invokevirtual 72	java/io/RandomAccessFile:close	()V
    //   89: aload_0
    //   90: getfield 21	com/facebook/soloader/t:f	Lcom/facebook/soloader/s;
    //   93: getfield 77	com/facebook/soloader/c:a	Ljava/io/File;
    //   96: invokestatic 90	com/facebook/soloader/SysUtil:c	(Ljava/io/File;)V
    //   99: aload_0
    //   100: getfield 29	com/facebook/soloader/t:d	Ljava/io/File;
    //   103: iconst_1
    //   104: invokestatic 95	com/facebook/soloader/s:b	(Ljava/io/File;B)V
    //   107: ldc 42
    //   109: new 97	java/lang/StringBuilder
    //   112: dup
    //   113: ldc 99
    //   115: invokespecial 102	java/lang/StringBuilder:<init>	(Ljava/lang/String;)V
    //   118: aload_0
    //   119: getfield 21	com/facebook/soloader/t:f	Lcom/facebook/soloader/s;
    //   122: getfield 77	com/facebook/soloader/c:a	Ljava/io/File;
    //   125: invokevirtual 106	java/lang/StringBuilder:append	(Ljava/lang/Object;)Ljava/lang/StringBuilder;
    //   128: ldc 108
    //   130: invokevirtual 111	java/lang/StringBuilder:append	(Ljava/lang/String;)Ljava/lang/StringBuilder;
    //   133: invokevirtual 115	java/lang/StringBuilder:toString	()Ljava/lang/String;
    //   136: invokestatic 50	android/util/Log:v	(Ljava/lang/String;Ljava/lang/String;)I
    //   139: pop
    //   140: aload_0
    //   141: getfield 31	com/facebook/soloader/t:e	Lcom/facebook/soloader/l;
    //   144: invokevirtual 118	com/facebook/soloader/l:close	()V
    //   147: return
    //   148: astore_2
    //   149: aload_2
    //   150: athrow
    //   151: astore_1
    //   152: aload_2
    //   153: ifnull +72 -> 225
    //   156: aload 4
    //   158: invokevirtual 72	java/io/RandomAccessFile:close	()V
    //   161: aload_1
    //   162: athrow
    //   163: astore_1
    //   164: ldc 42
    //   166: new 97	java/lang/StringBuilder
    //   169: dup
    //   170: ldc 99
    //   172: invokespecial 102	java/lang/StringBuilder:<init>	(Ljava/lang/String;)V
    //   175: aload_0
    //   176: getfield 21	com/facebook/soloader/t:f	Lcom/facebook/soloader/s;
    //   179: getfield 77	com/facebook/soloader/c:a	Ljava/io/File;
    //   182: invokevirtual 106	java/lang/StringBuilder:append	(Ljava/lang/Object;)Ljava/lang/StringBuilder;
    //   185: ldc 108
    //   187: invokevirtual 111	java/lang/StringBuilder:append	(Ljava/lang/String;)Ljava/lang/StringBuilder;
    //   190: invokevirtual 115	java/lang/StringBuilder:toString	()Ljava/lang/String;
    //   193: invokestatic 50	android/util/Log:v	(Ljava/lang/String;Ljava/lang/String;)I
    //   196: pop
    //   197: aload_0
    //   198: getfield 31	com/facebook/soloader/t:e	Lcom/facebook/soloader/l;
    //   201: invokevirtual 118	com/facebook/soloader/l:close	()V
    //   204: aload_1
    //   205: athrow
    //   206: astore_1
    //   207: new 120	java/lang/RuntimeException
    //   210: dup
    //   211: aload_1
    //   212: invokespecial 123	java/lang/RuntimeException:<init>	(Ljava/lang/Throwable;)V
    //   215: athrow
    //   216: astore_3
    //   217: aload_2
    //   218: aload_3
    //   219: invokestatic 129	com/facebook/androidcompat/AndroidCompat:addSuppressed	(Ljava/lang/Throwable;Ljava/lang/Throwable;)V
    //   222: goto -61 -> 161
    //   225: aload 4
    //   227: invokevirtual 72	java/io/RandomAccessFile:close	()V
    //   230: goto -69 -> 161
    //   233: astore_2
    //   234: aload_2
    //   235: athrow
    //   236: astore_1
    //   237: aload_2
    //   238: ifnull +18 -> 256
    //   241: aload_3
    //   242: invokevirtual 72	java/io/RandomAccessFile:close	()V
    //   245: aload_1
    //   246: athrow
    //   247: astore_3
    //   248: aload_2
    //   249: aload_3
    //   250: invokestatic 129	com/facebook/androidcompat/AndroidCompat:addSuppressed	(Ljava/lang/Throwable;Ljava/lang/Throwable;)V
    //   253: goto -8 -> 245
    //   256: aload_3
    //   257: invokevirtual 72	java/io/RandomAccessFile:close	()V
    //   260: goto -15 -> 245
    //   263: astore_1
    //   264: goto -27 -> 237
    //   267: astore_1
    //   268: aload_3
    //   269: astore_2
    //   270: goto -118 -> 152
    // Local variable table:
    //   start	length	slot	name	signature
    //   0	273	0	this	t
    //   151	11	1	localObject1	Object
    //   163	42	1	localObject2	Object
    //   206	6	1	localIOException	java.io.IOException
    //   236	10	1	localObject3	Object
    //   263	1	1	localObject4	Object
    //   267	1	1	localObject5	Object
    //   1	1	2	localObject6	Object
    //   148	70	2	localThrowable1	Throwable
    //   233	16	2	localThrowable2	Throwable
    //   269	1	2	localObject7	Object
    //   3	83	3	localRandomAccessFile1	java.io.RandomAccessFile
    //   216	26	3	localThrowable3	Throwable
    //   247	22	3	localThrowable4	Throwable
    //   25	201	4	localRandomAccessFile2	java.io.RandomAccessFile
    // Exception table:
    //   from	to	target	type
    //   27	46	148	java/lang/Throwable
    //   149	151	151	finally
    //   4	27	163	finally
    //   46	77	163	finally
    //   85	107	163	finally
    //   156	161	163	finally
    //   161	163	163	finally
    //   217	222	163	finally
    //   225	230	163	finally
    //   241	245	163	finally
    //   245	247	163	finally
    //   248	253	163	finally
    //   256	260	163	finally
    //   107	147	206	java/io/IOException
    //   164	206	206	java/io/IOException
    //   156	161	216	java/lang/Throwable
    //   77	85	233	java/lang/Throwable
    //   234	236	236	finally
    //   241	245	247	java/lang/Throwable
    //   77	85	263	finally
    //   27	46	267	finally
  }
}

/* Location:
 * Qualified Name:     com.facebook.soloader.t
 * Java Class Version: 6 (50.0)
 * JD-Core Version:    0.7.1
 */